Method name: <module>:
	    O:0, L:10          LOAD_CONST    0    
	    O:3, L:10       MAKE_FUNCTION    0    
	    O:6, L:10          STORE_NAME    0    // Value: formatweekday
	    O:9, L:15          LOAD_CONST    1    // Value: 1
	   O:12, L:15       MAKE_FUNCTION    0    
	   O:15, L:15          STORE_NAME    1    // Value: withas_bug
	   O:18, L:22          LOAD_CONST    2    // Value: 2
	   O:21, L:22       MAKE_FUNCTION    0    
	   O:24, L:22          STORE_NAME    2    // Value: test_invalid_registrations
	   O:27, L:29          LOAD_CONST    3    // Value: 3
	   O:30, L:29       MAKE_FUNCTION    0    
	   O:33, L:29          STORE_NAME    3    // Value: test_re_tests
	   O:36, L:36          LOAD_CONST    4    // Value: 4
	   O:39, L:36       MAKE_FUNCTION    0    
	   O:42, L:36          STORE_NAME    4    // Value: _gen_temp_sourcefile
	   O:45, L:36          LOAD_CONST    5    // Value: None
	   O:48, L:36        RETURN_VALUE         

Method name: <module>.formatweekday:
	    O:0, L:11           LOAD_FAST    0    // Value: self
	    O:3, L:11             DUP_TOP         
	    O:4, L:11           LOAD_ATTR    0    // Value: __exit__
	    O:7, L:11          STORE_FAST    1    // Value: _[2]
	   O:10, L:11           LOAD_ATTR    1    // Value: __enter__
	   O:13, L:11       CALL_FUNCTION    0    
	   O:16, L:11          STORE_FAST    2    // Value: _[1]
	   O:19, L:11       SETUP_FINALLY   39    // Value: 17
	   O:22, L:11           LOAD_FAST    2    // Value: _[1]
	   O:25, L:11         DELETE_FAST    2    // Value: _[1]
	   O:28, L:11          STORE_FAST    3    // Value: encoding
	   O:31, L:12           LOAD_FAST    3    // Value: encoding
	   O:34, L:12        RETURN_VALUE         
	   O:35, L:12           POP_BLOCK         
	   O:36, L:12          LOAD_CONST    0    // Value: None
	   O:39, L:12           LOAD_FAST    1    // Value: _[2]
	   O:42, L:12         DELETE_FAST    1    // Value: _[2]
	   O:45, L:12        WITH_CLEANUP         
	   O:46, L:12         END_FINALLY         
	   O:47, L:12          LOAD_CONST    0    // Value: None
	   O:50, L:12        RETURN_VALUE         

Method name: <module>.withas_bug:
	    O:0, L:16           LOAD_FAST    0    // Value: self
	    O:3, L:16           LOAD_ATTR    0    // Value: assertRaises
	    O:6, L:16         LOAD_GLOBAL    1    // Value: ZeroDivisionError
	    O:9, L:16       CALL_FUNCTION    1    
	   O:12, L:16             DUP_TOP         
	   O:13, L:16           LOAD_ATTR    2    // Value: __exit__
	   O:16, L:16          STORE_FAST    4    // Value: _[1]
	   O:19, L:16           LOAD_ATTR    3    // Value: __enter__
	   O:22, L:16       CALL_FUNCTION    0    
	   O:25, L:16             POP_TOP         
	   O:26, L:16       SETUP_FINALLY  105    // Value: 76
	   O:29, L:17           LOAD_FAST    1    // Value: nested
	   O:32, L:17           LOAD_FAST    2    // Value: a
	   O:35, L:17       CALL_FUNCTION    0    
	   O:38, L:17           LOAD_FAST    3    // Value: b
	   O:41, L:17       CALL_FUNCTION    0    
	   O:44, L:17       CALL_FUNCTION    2    
	   O:47, L:17             DUP_TOP         
	   O:48, L:17           LOAD_ATTR    2    // Value: __exit__
	   O:51, L:17          STORE_FAST    5    // Value: _[3]
	   O:54, L:17           LOAD_ATTR    3    // Value: __enter__
	   O:57, L:17       CALL_FUNCTION    0    
	   O:60, L:17          STORE_FAST    6    // Value: _[2]
	   O:63, L:17       SETUP_FINALLY   93    // Value: 27
	   O:66, L:17           LOAD_FAST    6    // Value: _[2]
	   O:69, L:17         DELETE_FAST    6    // Value: _[2]
	   O:72, L:17     UNPACK_SEQUENCE    2    
	   O:75, L:17          STORE_FAST    7    // Value: x
	   O:78, L:17          STORE_FAST    8    // Value: y
	   O:81, L:18          LOAD_CONST    1    // Value: 1
	   O:84, L:18          LOAD_CONST    2    // Value: 0
	   O:87, L:18 BINARY_FLOOR_DIVIDE         
	   O:88, L:18             POP_TOP         
	   O:89, L:18           POP_BLOCK         
	   O:90, L:18          LOAD_CONST    0    // Value: None
	   O:93, L:18           LOAD_FAST    5    // Value: _[3]
	   O:96, L:18         DELETE_FAST    5    // Value: _[3]
	   O:99, L:18        WITH_CLEANUP         
	  O:100, L:18         END_FINALLY         
	  O:101, L:18           POP_BLOCK         
	  O:102, L:18          LOAD_CONST    0    // Value: None
	  O:105, L:18           LOAD_FAST    4    // Value: _[1]
	  O:108, L:18         DELETE_FAST    4    // Value: _[1]
	  O:111, L:18        WITH_CLEANUP         
	  O:112, L:18         END_FINALLY         
	  O:113, L:18          LOAD_CONST    0    // Value: None
	  O:116, L:18        RETURN_VALUE         

Method name: <module>.test_invalid_registrations:
	    O:0, L:23          LOAD_CONST    0    // Value: None
	    O:3, L:23        RETURN_VALUE         
	    O:4, L:24           LOAD_FAST    0    // Value: x
	    O:7, L:24             DUP_TOP         
	    O:8, L:24           LOAD_ATTR    0    // Value: __exit__
	   O:11, L:24          STORE_FAST    1    // Value: _[1]
	   O:14, L:24           LOAD_ATTR    1    // Value: __enter__
	   O:17, L:24       CALL_FUNCTION    0    
	   O:20, L:24             POP_TOP         
	   O:21, L:24       SETUP_FINALLY   34    // Value: 10
	   O:24, L:25          LOAD_CONST    1    // Value: 1
	   O:27, L:25          STORE_FAST    0    // Value: x
	   O:30, L:25           POP_BLOCK         
	   O:31, L:25          LOAD_CONST    0    // Value: None
	   O:34, L:25           LOAD_FAST    1    // Value: _[1]
	   O:37, L:25         DELETE_FAST    1    // Value: _[1]
	   O:40, L:25        WITH_CLEANUP         
	   O:41, L:25         END_FINALLY         
	   O:42, L:25          LOAD_CONST    0    // Value: None
	   O:45, L:25        RETURN_VALUE         

Method name: <module>.test_re_tests:
	    O:0, L:30          SETUP_LOOP   52    // Value: 49
	    O:3, L:30           LOAD_FAST    0    // Value: tests
	    O:6, L:30            GET_ITER         
	    O:7, L:30            FOR_ITER   51    // Value: 41
	   O:10, L:30          STORE_FAST    1    // Value: t
	   O:13, L:31         LOAD_GLOBAL    0    // Value: a
	   O:16, L:31             DUP_TOP         
	   O:17, L:31           LOAD_ATTR    1    // Value: __exit__
	   O:20, L:31          STORE_FAST    2    // Value: _[1]
	   O:23, L:31           LOAD_ATTR    2    // Value: __enter__
	   O:26, L:31       CALL_FUNCTION    0    
	   O:29, L:31             POP_TOP         
	   O:30, L:31       SETUP_FINALLY   40    // Value: 7
	   O:33, L:32       CONTINUE_LOOP    7    
	   O:36, L:32           POP_BLOCK         
	   O:37, L:32          LOAD_CONST    0    // Value: None
	   O:40, L:32           LOAD_FAST    2    // Value: _[1]
	   O:43, L:32         DELETE_FAST    2    // Value: _[1]
	   O:46, L:32        WITH_CLEANUP         
	   O:47, L:32         END_FINALLY         
	   O:48, L:32       JUMP_ABSOLUTE    7    
	   O:51, L:32           POP_BLOCK         
	   O:52, L:32          LOAD_CONST    0    // Value: None
	   O:55, L:32        RETURN_VALUE         

Method name: <module>._gen_temp_sourcefile:
	    O:0, L:37           LOAD_FAST    0    // Value: x
	    O:3, L:37             DUP_TOP         
	    O:4, L:37           LOAD_ATTR    0    // Value: __exit__
	    O:7, L:37          STORE_FAST    4    // Value: _[2]
	   O:10, L:37           LOAD_ATTR    1    // Value: __enter__
	   O:13, L:37       CALL_FUNCTION    0    
	   O:16, L:37          STORE_FAST    5    // Value: _[1]
	   O:19, L:37       SETUP_FINALLY   52    // Value: 30
	   O:22, L:37           LOAD_FAST    5    // Value: _[1]
	   O:25, L:37         DELETE_FAST    5    // Value: _[1]
	   O:28, L:37          STORE_FAST    6    // Value: y
	   O:31, L:38           LOAD_FAST    1    // Value: a
	   O:34, L:38       JUMP_IF_FALSE   47    // Value: 10
	   O:37, L:38             POP_TOP         
	   O:38, L:39          LOAD_CONST    1    // Value: 2
	   O:41, L:39          STORE_FAST    6    // Value: y
	   O:44, L:39        JUMP_FORWARD   48    // Value: 1
	   O:47, L:39             POP_TOP         
	   O:48, L:39           POP_BLOCK         
	   O:49, L:39          LOAD_CONST    0    // Value: None
	   O:52, L:39           LOAD_FAST    4    // Value: _[2]
	   O:55, L:39         DELETE_FAST    4    // Value: _[2]
	   O:58, L:39        WITH_CLEANUP         
	   O:59, L:39         END_FINALLY         
	   O:60, L:40          LOAD_CONST    2    // Value: 5
	   O:63, L:40        RETURN_VALUE         
