Method name: <module>:
	    O:0, L:19          LOAD_CONST    0    // Value: 0
	    O:2, L:19          LOAD_CONST    1    // Value: (wraps)
	    O:4, L:19         IMPORT_NAME    0    // Value: functools
	    O:6, L:19         IMPORT_FROM    1    // Value: wraps
	    O:8, L:19          STORE_NAME    1    // Value: wraps
	   O:10, L:19             POP_TOP         
	   O:12, L:21    LOAD_BUILD_CLASS         
	   O:14, L:21          LOAD_CONST    2    // Value: 2
	   O:16, L:21          LOAD_CONST    3    // Value: "ContextDecorator"
	   O:18, L:21       MAKE_FUNCTION    0    
	   O:20, L:21          LOAD_CONST    3    // Value: "ContextDecorator"
	   O:22, L:21           LOAD_NAME    2    // Value: object
	   O:24, L:21       CALL_FUNCTION    3    
	   O:26, L:21          STORE_NAME    3    // Value: ContextDecorator
	   O:28, L:21          LOAD_CONST    4    // Value: None
	   O:30, L:21        RETURN_VALUE         

Method name: <module>.ContextDecorator:
	    O:0, L:21           LOAD_NAME    0    // Value: __name__
	    O:2, L:21          STORE_NAME    1    // Value: __module__
	    O:4, L:21          LOAD_CONST    0    // Value: "ContextDecorator"
	    O:6, L:21          STORE_NAME    2    // Value: __qualname__
	    O:8, L:22          LOAD_CONST    1    // Value: 1
	   O:10, L:22          LOAD_CONST    2    // Value: "ContextDecorator.__call__"
	   O:12, L:22       MAKE_FUNCTION    0    
	   O:14, L:22          STORE_NAME    3    // Value: __call__
	   O:16, L:22          LOAD_CONST    3    // Value: None
	   O:18, L:22        RETURN_VALUE         

Method name: <module>.ContextDecorator.__call__:
	    O:0, L:23         LOAD_GLOBAL    0    // Value: wraps
	    O:2, L:23          LOAD_DEREF    0    // Value: null
	    O:4, L:23       CALL_FUNCTION    1    
	    O:6, L:23        LOAD_CLOSURE    0    // Value: null
	    O:8, L:23        LOAD_CLOSURE    1    // Value: null
	   O:10, L:23         BUILD_TUPLE    2    
	   O:12, L:23          LOAD_CONST    1    // Value: 1
	   O:14, L:23          LOAD_CONST    2    // Value: "ContextDecorator.__call__.<locals>.inner"
	   O:16, L:23       MAKE_FUNCTION    8    
	   O:18, L:23       CALL_FUNCTION    1    
	   O:20, L:23          STORE_FAST    2    // Value: inner
	   O:22, L:27           LOAD_FAST    2    // Value: inner
	   O:24, L:27        RETURN_VALUE         

Method name: <module>.ContextDecorator.__call__.inner:
	    O:0, L:25          LOAD_DEREF    1    // Value: null
	    O:2, L:25           LOAD_ATTR    0    // Value: _recreate_cm
	    O:4, L:25       CALL_FUNCTION    0    
	    O:6, L:25          SETUP_WITH   21    // Value: 12
	    O:8, L:25             POP_TOP         
	   O:10, L:26          LOAD_DEREF    0    // Value: null
	   O:12, L:26           LOAD_FAST    0    // Value: args
	   O:14, L:26           LOAD_FAST    1    // Value: kwds
	   O:16, L:26    CALL_FUNCTION_EX    1    
	   O:18, L:26        RETURN_VALUE         
	   O:20, L:26  WITH_CLEANUP_START         
	   O:22, L:26 WITH_CLEANUP_FINISH         
	   O:24, L:26         END_FINALLY         
	   O:26, L:26          LOAD_CONST    0    // Value: None
	   O:28, L:26        RETURN_VALUE         
